pyerr/__init__.py
pyerr/pyerr.py
tests/__init__.py
tests/test_pyerr.py
pyerr-0.1.1.dist-info/LICENSE
pyerr-0.1.1.dist-info/METADATA
pyerr-0.1.1.dist-info/WHEEL
pyerr-0.1.1.dist-info/top_level.txt
pyerr-0.1.1.dist-info/RECORD
